commition-0.0.2.dist-info/METADATA
commition-0.0.2.dist-info/WHEEL
commition-0.0.2.dist-info/entry_points.txt
commition-0.0.2.dist-info/licenses/LICENSE.md
commition/__init__.py
commition/_compile.py
commition/_version.py
commition/error.py
commition/plugin/__init__.py
commition/plugin/_git.py
commition/plugin/_installed.py
commition/plugin/_match.py
commition/plugin/pdm.py
commition-0.0.2.dist-info/RECORD
