Metadata-Version: 2.1
Name: commition
Version: 0.0.2
Summary: Commit only software versioning (based on conventional commits)
Author: nosludge
Maintainer: nosludge
License: Apache License
Classifier: Development Status :: 2 - Pre-Alpha
Classifier: Intended Audience :: Developers
Classifier: License :: OSI Approved :: Apache Software License
Classifier: Programming Language :: Python
Classifier: Programming Language :: Python :: 3 :: Only
Classifier: Programming Language :: Python :: 3.11
Classifier: Programming Language :: Python :: 3.12
Classifier: Programming Language :: Python :: 3.13
Classifier: Topic :: Software Development :: Libraries
Classifier: Topic :: Software Development :: Libraries :: Python Modules
Classifier: Typing :: Typed
Project-URL: Changelog, https://github.com/nosludge/commition/blob/master/CHANGELOG.md
Project-URL: Documentation, https://nosludge.github.io/commition
Project-URL: Homepage, https://nosludge.github.io/commition
Project-URL: Issues, https://github.com/nosludge/commition/issues
Project-URL: Repository, https://github.com/nosludge/commition
Requires-Python: >=3.11
Provides-Extra: all
Requires-Dist: gitpython>=3; extra == "all"
Requires-Dist: tooload>=0.0.1; extra == "all"
Provides-Extra: git
Requires-Dist: gitpython>=3; extra == "git"
Provides-Extra: pdm
Requires-Dist: gitpython>=3; extra == "pdm"
Requires-Dist: tooload>=0.0.1; extra == "pdm"
